eykturkish/__init__.py
eykturkish/basic.py
eykturkish/colors.py
eykturkish/eykturkish.py
eykturkish/matematik.py
eykturkish/unicodelib.py
eykturkish-0.1.13.dist-info/licenses/LICENSE.md
eykturkish-0.1.13.dist-info/METADATA
eykturkish-0.1.13.dist-info/WHEEL
eykturkish-0.1.13.dist-info/top_level.txt
eykturkish-0.1.13.dist-info/RECORD
