Metadata-Version: 2.4
Name: eykturkish
Version: 0.1.13
Summary: Hata dayanıklılığı sunan ve Türkçe dil desteği içeren bir yardımcı kütüphanedir. (CC BY-ND 4.0 lisanslıdır).
Author: Eymen
License-Expression: CC-BY-ND-4.0
Keywords: turkish,language,nlp,eyk,utility,crash-proof,thread-unsafe,cc-by-nd,helpful
Classifier: Development Status :: 4 - Beta
Classifier: Operating System :: OS Independent
Classifier: Intended Audience :: Developers
Classifier: Topic :: Software Development :: Libraries :: Python Modules
Classifier: Natural Language :: Turkish
Classifier: Programming Language :: Python :: 3
Classifier: Programming Language :: Python :: 3 :: Only
Classifier: Programming Language :: Python :: 3.5
Classifier: Programming Language :: Python :: 3.6
Classifier: Programming Language :: Python :: 3.7
Classifier: Programming Language :: Python :: 3.8
Classifier: Programming Language :: Python :: 3.9
Classifier: Programming Language :: Python :: 3.10
Classifier: Programming Language :: Python :: 3.11
Classifier: Programming Language :: Python :: 3.12
Classifier: Programming Language :: Python :: 3.13
Requires-Python: >=3.5
License-File: LICENSE.md
Dynamic: license-file
